pretty_langchain/__init__.py
pretty_langchain-0.1.0.dist-info/LICENSE
pretty_langchain-0.1.0.dist-info/METADATA
pretty_langchain-0.1.0.dist-info/WHEEL
pretty_langchain-0.1.0.dist-info/RECORD
